covidcloud_search/__init__.py
covidcloud_search/search.py
search_python_client/__init__.py
search_python_client/search.py
search_python_client-0.1.9.dist-info/METADATA
search_python_client-0.1.9.dist-info/WHEEL
search_python_client-0.1.9.dist-info/top_level.txt
search_python_client-0.1.9.dist-info/RECORD
