Metadata-Version: 2.1
Name: search-python-client
Version: 0.1.9
Summary: DNAstack Search Library
Home-page: UNKNOWN
Author: Ayman A
Author-email: UNKNOWN
License: MIT
Platform: UNKNOWN
Requires-Dist: requests (>=2.0.0)
Requires-Dist: pandas (>=1.0.0)
